cert_uploader/__init__.py
cert_uploader/certificate.py
cert_uploader/cli.py
cert_uploader/exceptions.py
cert_uploader/scan.py
cert_uploader/version.py
cert_uploader/uploader/__init__.py
cert_uploader/uploader/acm.py
cert_uploader/uploader/base.py
cert_uploader/uploader/iam.py
cert_uploader-1.1.12.dist-info/METADATA
cert_uploader-1.1.12.dist-info/WHEEL
cert_uploader-1.1.12.dist-info/entry_points.txt
cert_uploader-1.1.12.dist-info/top_level.txt
cert_uploader-1.1.12.dist-info/RECORD
