Metadata-Version: 2.1
Name: cert-uploader
Version: 1.1.12
Summary: Upload ACM/IAM Server Certificates to AWS and apply them to ELBs
Home-page: https://github.com/GESkunkworks/cert-uploader
Author: Michael Palmer
Author-email: github@michaeldpalmer.com
License: UNKNOWN
Keywords: certificate cert uploader tools aws iam acm
Platform: UNKNOWN
Classifier: Programming Language :: Python :: 2.7
Classifier: Programming Language :: Python :: 3.6
Classifier: Development Status :: 5 - Production/Stable
Classifier: Topic :: Utilities
Requires-Dist: boto3 (~=1.7.16)
Requires-Dist: cryptography (~=2.3.0)
Requires-Dist: pyOpenSSL (~=17.5.0)
Requires-Dist: six (~=1.11.0)
Requires-Dist: scandir (~=1.7); python_version < "3.0"
